{"status":"done","chunks":{"main":[{"name":"main-f18fb3949fbbdea625f0.js","path":"F:\\Django\\dnd_machine\\dnd_machine\\assets\\bundles\\main-f18fb3949fbbdea625f0.js"}]},"error":"ModuleBuildError","message":"Module build failed: SyntaxError: F:/Django/dnd_machine/dnd_machine/assets/js/index.js: Unexpected token, expected ; (354:12)\n\n  352 |         let proficiencies_array = []\n  353 |         for (let i = 0; i < this.state.class_items.saving_throwsproficiencies\n> 354 |             proficiencies_array.push(<input type=\"hidden\" name={'proficiencies' + i} value={this.state.class_items.proficiencies[i]['proficiency']} />)\n      |             ^\n  355 |         }\n  356 |         return proficiencies_array\n  357 |     }\n"}